Metadata-Version: 2.1
Name: shz-types
Version: 0.0.4
Summary: Personal types for my projects
Author: Eliseu Brito
Author-email: eliseubrito776@gmail.com
License: MIT License
Keywords: shz types shztypes shz_types
License-File: LICENSE
